{
	"highscores": {
		"world": "Vunira",
		"category": "experience",
		"vocation": "paladins",
		"highscore_list": [
			{
				"rank": 1,
				"name": "Partyboost",
				"vocation": "Royal Paladin",
				"world": "Vunira",
				"level": 2051,
				"value": 143469023391
			},
			{
				"rank": 2,
				"name": "True Abdosz",
				"vocation": "Royal Paladin",
				"world": "Vunira",
				"level": 1646,
				"value": 74189259902
			},
			{
				"rank": 3,
				"name": "Sinsor",
				"vocation": "Royal Paladin",
				"world": "Vunira",
				"level": 1624,
				"value": 71191763196
			},
			{
				"rank": 4,
				"name": "Sabziro",
				"vocation": "Royal Paladin",
				"world": "Vunira",
				"level": 1623,
				"value": 71049380846
			},
			{
				"rank": 5,
				"name": "Nozyk",
				"vocation": "Royal Paladin",
				"world": "Vunira",
				"level": 1582,
				"value": 65836897671
			},
			{
				"rank": 6,
				"name": "Alex Froggy",
				"vocation": "Royal Paladin",
				"world": "Vunira",
				"level": 1565,
				"value": 63708034125
			},
			{
				"rank": 7,
				"name": "Saint Tristen",
				"vocation": "Royal Paladin",
				"world": "Vunira",
				"level": 1532,
				"value": 59704262695
			},
			{
				"rank": 8,
				"name": "Mathias Bynens",
				"vocation": "Royal Paladin",
				"world": "Vunira",
				"level": 1475,
				"value": 53314662512
			},
			{
				"rank": 9,
				"name": "Radraz",
				"vocation": "Royal Paladin",
				"world": "Vunira",
				"level": 1452,
				"value": 50842611092
			},
			{
				"rank": 10,
				"name": "Lanchadanan",
				"vocation": "Royal Paladin",
				"world": "Vunira",
				"level": 1400,
				"value": 45578122064
			},
			{
				"rank": 11,
				"name": "Reo Light",
				"vocation": "Royal Paladin",
				"world": "Vunira",
				"level": 1392,
				"value": 44803981306
			},
			{
				"rank": 12,
				"name": "Bea Charlover Aca",
				"vocation": "Royal Paladin",
				"world": "Vunira",
				"level": 1365,
				"value": 42292876418
			},
			{
				"rank": 13,
				"name": "Yes Yes",
				"vocation": "Royal Paladin",
				"world": "Vunira",
				"level": 1346,
				"value": 40499482860
			},
			{
				"rank": 14,
				"name": "Wojjtekk",
				"vocation": "Royal Paladin",
				"world": "Vunira",
				"level": 1335,
				"value": 39527286680
			},
			{
				"rank": 15,
				"name": "Mad Bully",
				"vocation": "Royal Paladin",
				"world": "Vunira",
				"level": 1323,
				"value": 38479385398
			},
			{
				"rank": 16,
				"name": "Pastor Koylu",
				"vocation": "Royal Paladin",
				"world": "Vunira",
				"level": 1321,
				"value": 38297907724
			},
			{
				"rank": 17,
				"name": "Zoxerr",
				"vocation": "Royal Paladin",
				"world": "Vunira",
				"level": 1311,
				"value": 37383541216
			},
			{
				"rank": 18,
				"name": "Kimpsuu",
				"vocation": "Royal Paladin",
				"world": "Vunira",
				"level": 1293,
				"value": 35937391250
			},
			{
				"rank": 19,
				"name": "Bluemoon Kimimaro",
				"vocation": "Royal Paladin",
				"world": "Vunira",
				"level": 1274,
				"value": 34318209983
			},
			{
				"rank": 20,
				"name": "Linkirvana",
				"vocation": "Royal Paladin",
				"world": "Vunira",
				"level": 1269,
				"value": 33931770450
			},
			{
				"rank": 21,
				"name": "Bastu Boris",
				"vocation": "Royal Paladin",
				"world": "Vunira",
				"level": 1256,
				"value": 32880821940
			},
			{
				"rank": 22,
				"name": "Anardiel",
				"vocation": "Royal Paladin",
				"world": "Vunira",
				"level": 1241,
				"value": 31753159809
			},
			{
				"rank": 23,
				"name": "Darklight Holy Cast",
				"vocation": "Royal Paladin",
				"world": "Vunira",
				"level": 1223,
				"value": 30371438032
			},
			{
				"rank": 24,
				"name": "Royal druidiaaa",
				"vocation": "Royal Paladin",
				"world": "Vunira",
				"level": 1219,
				"value": 30073573450
			},
			{
				"rank": 25,
				"name": "Super Pinchito",
				"vocation": "Paladin",
				"world": "Vunira",
				"level": 1214,
				"value": 29724440098
			},
			{
				"rank": 26,
				"name": "Lakroz",
				"vocation": "Royal Paladin",
				"world": "Vunira",
				"level": 1213,
				"value": 29629491598
			},
			{
				"rank": 27,
				"name": "Gunner Konrad",
				"vocation": "Royal Paladin",
				"world": "Vunira",
				"level": 1158,
				"value": 25792264428
			},
			{
				"rank": 28,
				"name": "Mega Marjan",
				"vocation": "Royal Paladin",
				"world": "Vunira",
				"level": 1158,
				"value": 25786725736
			},
			{
				"rank": 29,
				"name": "Overlord Dagnars",
				"vocation": "Royal Paladin",
				"world": "Vunira",
				"level": 1152,
				"value": 25392960256
			},
			{
				"rank": 30,
				"name": "Gnoors",
				"vocation": "Royal Paladin",
				"world": "Vunira",
				"level": 1152,
				"value": 25388427001
			},
			{
				"rank": 31,
				"name": "Vexiki",
				"vocation": "Royal Paladin",
				"world": "Vunira",
				"level": 1150,
				"value": 25229629049
			},
			{
				"rank": 32,
				"name": "Carpo",
				"vocation": "Royal Paladin",
				"world": "Vunira",
				"level": 1145,
				"value": 24914326639
			},
			{
				"rank": 33,
				"name": "Venus",
				"vocation": "Royal Paladin",
				"world": "Vunira",
				"level": 1142,
				"value": 24701269194
			},
			{
				"rank": 34,
				"name": "Alriken",
				"vocation": "Royal Paladin",
				"world": "Vunira",
				"level": 1142,
				"value": 24699645802
			},
			{
				"rank": 35,
				"name": "Strukem",
				"vocation": "Royal Paladin",
				"world": "Vunira",
				"level": 1138,
				"value": 24493254126
			},
			{
				"rank": 36,
				"name": "Glockad",
				"vocation": "Royal Paladin",
				"world": "Vunira",
				"level": 1108,
				"value": 22549818554
			},
			{
				"rank": 37,
				"name": "Draakz",
				"vocation": "Royal Paladin",
				"world": "Vunira",
				"level": 1092,
				"value": 21632474495
			},
			{
				"rank": 38,
				"name": "Mazzika Raa",
				"vocation": "Royal Paladin",
				"world": "Vunira",
				"level": 1092,
				"value": 21620767966
			},
			{
				"rank": 39,
				"name": "Claq",
				"vocation": "Royal Paladin",
				"world": "Vunira",
				"level": 1084,
				"value": 21149947044
			},
			{
				"rank": 40,
				"name": "Crim Moon",
				"vocation": "Royal Paladin",
				"world": "Vunira",
				"level": 1070,
				"value": 20335466081
			},
			{
				"rank": 41,
				"name": "Tad Dzik",
				"vocation": "Royal Paladin",
				"world": "Vunira",
				"level": 1051,
				"value": 19283444306
			},
			{
				"rank": 42,
				"name": "Kubus Oficjalnie",
				"vocation": "Royal Paladin",
				"world": "Vunira",
				"level": 1047,
				"value": 19026024683
			},
			{
				"rank": 43,
				"name": "Pan Szympans",
				"vocation": "Royal Paladin",
				"world": "Vunira",
				"level": 1045,
				"value": 18921746369
			},
			{
				"rank": 44,
				"name": "King Baani",
				"vocation": "Royal Paladin",
				"world": "Vunira",
				"level": 1033,
				"value": 18288969140
			},
			{
				"rank": 45,
				"name": "Vic Del'Sal",
				"vocation": "Royal Paladin",
				"world": "Vunira",
				"level": 1033,
				"value": 18269245105
			},
			{
				"rank": 46,
				"name": "Krysson",
				"vocation": "Royal Paladin",
				"world": "Vunira",
				"level": 1031,
				"value": 18203226350
			},
			{
				"rank": 47,
				"name": "Gala Tuga",
				"vocation": "Royal Paladin",
				"world": "Vunira",
				"level": 1027,
				"value": 17972583836
			},
			{
				"rank": 48,
				"name": "Maan Temor",
				"vocation": "Royal Paladin",
				"world": "Vunira",
				"level": 1023,
				"value": 17759501327
			},
			{
				"rank": 49,
				"name": "Incun",
				"vocation": "Royal Paladin",
				"world": "Vunira",
				"level": 1017,
				"value": 17473209296
			},
			{
				"rank": 50,
				"name": "Lukehimself",
				"vocation": "Royal Paladin",
				"world": "Vunira",
				"level": 1015,
				"value": 17363308508
			}
		],
		"highscore_page": {
			"current_page": 1,
			"total_pages": 20,
			"total_records": 1000
		}
	},
	"information": {
		"api": {
			"version": 4,
			"release": "edge",
			"commit": "e8db71b9c123ed87aabee9cbe244f3beddd33950"
		},
		"tibia_urls": [
			"https://www.tibia.com/community/?subtopic=highscores&world=Vunira&category=6&profession=3&currentpage=1"
		],
		"status": {
			"http_code": 200
		}
	}
}
