{
	"highscores": {
		"world": "Vunira",
		"category": "experience",
		"vocation": "paladins",
		"highscore_list": [
			{
				"rank": 1,
				"name": "Partyboost",
				"vocation": "Royal Paladin",
				"world": "Vunira",
				"level": 1867,
				"value": 108171591361
			},
			{
				"rank": 2,
				"name": "True Abdosz",
				"vocation": "Royal Paladin",
				"world": "Vunira",
				"level": 1523,
				"value": 58681837940
			},
			{
				"rank": 3,
				"name": "Sinsor",
				"vocation": "Royal Paladin",
				"world": "Vunira",
				"level": 1513,
				"value": 57521144461
			},
			{
				"rank": 4,
				"name": "Sabziro",
				"vocation": "Royal Paladin",
				"world": "Vunira",
				"level": 1492,
				"value": 55217429916
			},
			{
				"rank": 5,
				"name": "Saint Tristen",
				"vocation": "Royal Paladin",
				"world": "Vunira",
				"level": 1473,
				"value": 53099878779
			},
			{
				"rank": 6,
				"name": "Nozyk",
				"vocation": "Royal Paladin",
				"world": "Vunira",
				"level": 1409,
				"value": 46448526231
			},
			{
				"rank": 7,
				"name": "Alex Froggy",
				"vocation": "Royal Paladin",
				"world": "Vunira",
				"level": 1377,
				"value": 43419150587
			},
			{
				"rank": 8,
				"name": "Paladino Do luz",
				"vocation": "Royal Paladin",
				"world": "Vunira",
				"level": 1345,
				"value": 40442959237
			},
			{
				"rank": 9,
				"name": "Lanchadanan",
				"vocation": "Royal Paladin",
				"world": "Vunira",
				"level": 1333,
				"value": 39307626623
			},
			{
				"rank": 10,
				"name": "Roffberto",
				"vocation": "Royal Paladin",
				"world": "Vunira",
				"level": 1313,
				"value": 37638743363
			},
			{
				"rank": 11,
				"name": "Soluberto",
				"vocation": "Royal Paladin",
				"world": "Vunira",
				"level": 1303,
				"value": 36718759105
			},
			{
				"rank": 12,
				"name": "Reo Light",
				"vocation": "Royal Paladin",
				"world": "Vunira",
				"level": 1298,
				"value": 36335904809
			},
			{
				"rank": 13,
				"name": "Linkirvana",
				"vocation": "Royal Paladin",
				"world": "Vunira",
				"level": 1269,
				"value": 33931770450
			},
			{
				"rank": 14,
				"name": "Zoxerr",
				"vocation": "Royal Paladin",
				"world": "Vunira",
				"level": 1256,
				"value": 32907095141
			},
			{
				"rank": 15,
				"name": "Anardiel",
				"vocation": "Royal Paladin",
				"world": "Vunira",
				"level": 1233,
				"value": 31108503184
			},
			{
				"rank": 16,
				"name": "Mathias Bynens",
				"vocation": "Royal Paladin",
				"world": "Vunira",
				"level": 1229,
				"value": 30801511989
			},
			{
				"rank": 17,
				"name": "Yes Yes",
				"vocation": "Royal Paladin",
				"world": "Vunira",
				"level": 1222,
				"value": 30331045680
			},
			{
				"rank": 18,
				"name": "Pastor Koylu",
				"vocation": "Royal Paladin",
				"world": "Vunira",
				"level": 1200,
				"value": 28691975821
			},
			{
				"rank": 19,
				"name": "Bea Charlover Aca",
				"vocation": "Royal Paladin",
				"world": "Vunira",
				"level": 1200,
				"value": 28665208526
			},
			{
				"rank": 20,
				"name": "Lakroz",
				"vocation": "Royal Paladin",
				"world": "Vunira",
				"level": 1189,
				"value": 27895514326
			},
			{
				"rank": 21,
				"name": "Namikaze Kimimaro",
				"vocation": "Royal Paladin",
				"world": "Vunira",
				"level": 1166,
				"value": 26321829987
			},
			{
				"rank": 22,
				"name": "Kimpsuu",
				"vocation": "Royal Paladin",
				"world": "Vunira",
				"level": 1162,
				"value": 26041876147
			},
			{
				"rank": 23,
				"name": "Bing Lao",
				"vocation": "Royal Paladin",
				"world": "Vunira",
				"level": 1140,
				"value": 24611779202
			},
			{
				"rank": 24,
				"name": "Gubb Sam",
				"vocation": "Royal Paladin",
				"world": "Vunira",
				"level": 1123,
				"value": 23525621676
			},
			{
				"rank": 25,
				"name": "Royal druidiaaa",
				"vocation": "Royal Paladin",
				"world": "Vunira",
				"level": 1123,
				"value": 23478777679
			},
			{
				"rank": 26,
				"name": "Wojjtekk",
				"vocation": "Royal Paladin",
				"world": "Vunira",
				"level": 1122,
				"value": 23464024753
			},
			{
				"rank": 27,
				"name": "Super Pinchito",
				"vocation": "Royal Paladin",
				"world": "Vunira",
				"level": 1119,
				"value": 23277706413
			},
			{
				"rank": 28,
				"name": "Venus",
				"vocation": "Royal Paladin",
				"world": "Vunira",
				"level": 1103,
				"value": 22288375645
			},
			{
				"rank": 29,
				"name": "Exevus",
				"vocation": "Royal Paladin",
				"world": "Vunira",
				"level": 1098,
				"value": 21945256366
			},
			{
				"rank": 30,
				"name": "Claq",
				"vocation": "Royal Paladin",
				"world": "Vunira",
				"level": 1076,
				"value": 20702980365
			},
			{
				"rank": 31,
				"name": "Struke",
				"vocation": "Royal Paladin",
				"world": "Vunira",
				"level": 1068,
				"value": 20238848763
			},
			{
				"rank": 32,
				"name": "Crim Moon",
				"vocation": "Royal Paladin",
				"world": "Vunira",
				"level": 1066,
				"value": 20108946949
			},
			{
				"rank": 33,
				"name": "Mega Marjan",
				"vocation": "Royal Paladin",
				"world": "Vunira",
				"level": 1057,
				"value": 19597530756
			},
			{
				"rank": 34,
				"name": "Boris Bierdole",
				"vocation": "Royal Paladin",
				"world": "Vunira",
				"level": 1032,
				"value": 18262603992
			},
			{
				"rank": 35,
				"name": "Vic Del'Sal",
				"vocation": "Royal Paladin",
				"world": "Vunira",
				"level": 1029,
				"value": 18081069489
			},
			{
				"rank": 36,
				"name": "Royal For salee",
				"vocation": "Royal Paladin",
				"world": "Vunira",
				"level": 1026,
				"value": 17927617399
			},
			{
				"rank": 37,
				"name": "Draakz",
				"vocation": "Royal Paladin",
				"world": "Vunira",
				"level": 1024,
				"value": 17794921599
			},
			{
				"rank": 38,
				"name": "War Fiend",
				"vocation": "Royal Paladin",
				"world": "Vunira",
				"level": 1024,
				"value": 17791219810
			},
			{
				"rank": 39,
				"name": "Chief Detox",
				"vocation": "Royal Paladin",
				"world": "Vunira",
				"level": 1019,
				"value": 17565651517
			},
			{
				"rank": 40,
				"name": "Gala Tuga",
				"vocation": "Royal Paladin",
				"world": "Vunira",
				"level": 1016,
				"value": 17413228758
			},
			{
				"rank": 41,
				"name": "Mazzika Raa",
				"vocation": "Royal Paladin",
				"world": "Vunira",
				"level": 1015,
				"value": 17371977646
			},
			{
				"rank": 42,
				"name": "Lukehimself",
				"vocation": "Royal Paladin",
				"world": "Vunira",
				"level": 1013,
				"value": 17224739177
			},
			{
				"rank": 43,
				"name": "Alriken",
				"vocation": "Royal Paladin",
				"world": "Vunira",
				"level": 1012,
				"value": 17177653642
			},
			{
				"rank": 44,
				"name": "Ladyy Aias",
				"vocation": "Royal Paladin",
				"world": "Vunira",
				"level": 1005,
				"value": 16837534490
			},
			{
				"rank": 45,
				"name": "Spawacz Oblivion",
				"vocation": "Royal Paladin",
				"world": "Vunira",
				"level": 1002,
				"value": 16713599670
			},
			{
				"rank": 46,
				"name": "King Baani",
				"vocation": "Royal Paladin",
				"world": "Vunira",
				"level": 1000,
				"value": 16601361090
			},
			{
				"rank": 47,
				"name": "Pan Szympans",
				"vocation": "Royal Paladin",
				"world": "Vunira",
				"level": 988,
				"value": 16000823824
			},
			{
				"rank": 48,
				"name": "Deexter",
				"vocation": "Royal Paladin",
				"world": "Vunira",
				"level": 982,
				"value": 15710508517
			},
			{
				"rank": 49,
				"name": "Krasnall",
				"vocation": "Royal Paladin",
				"world": "Vunira",
				"level": 968,
				"value": 15031432409
			},
			{
				"rank": 50,
				"name": "Zagnus Ened",
				"vocation": "Royal Paladin",
				"world": "Vunira",
				"level": 958,
				"value": 14579986375
			}
		],
		"highscore_page": {
			"current_page": 1,
			"total_pages": 20,
			"total_records": 1000
		}
	},
	"information": {
		"api": {
			"version": 4,
			"release": "edge",
			"commit": "6187ad5ef149cb0508385213810e062dbbd7df0d"
		},
		"tibia_urls": [
			"https://www.tibia.com/community/?subtopic=highscores&world=Vunira&category=6&profession=3&currentpage=1"
		],
		"status": {
			"http_code": 200
		}
	}
}
