{
	"highscores": {
		"world": "Vunira",
		"category": "experience",
		"vocation": "paladins",
		"highscore_list": [
			{
				"rank": 1,
				"name": "Partyboost",
				"vocation": "Royal Paladin",
				"world": "Vunira",
				"level": 2066,
				"value": 146682593579
			},
			{
				"rank": 2,
				"name": "Not Radraz",
				"vocation": "Royal Paladin",
				"world": "Vunira",
				"level": 1811,
				"value": 98770153547
			},
			{
				"rank": 3,
				"name": "True Abdosz",
				"vocation": "Royal Paladin",
				"world": "Vunira",
				"level": 1686,
				"value": 79599195580
			},
			{
				"rank": 4,
				"name": "Sabziro",
				"vocation": "Royal Paladin",
				"world": "Vunira",
				"level": 1665,
				"value": 76713945035
			},
			{
				"rank": 5,
				"name": "Sinsor",
				"vocation": "Royal Paladin",
				"world": "Vunira",
				"level": 1650,
				"value": 74654322104
			},
			{
				"rank": 6,
				"name": "Nozyk",
				"vocation": "Royal Paladin",
				"world": "Vunira",
				"level": 1639,
				"value": 73125829643
			},
			{
				"rank": 7,
				"name": "Alex Froggy",
				"vocation": "Royal Paladin",
				"world": "Vunira",
				"level": 1629,
				"value": 71899763106
			},
			{
				"rank": 8,
				"name": "Saint Tristen",
				"vocation": "Royal Paladin",
				"world": "Vunira",
				"level": 1544,
				"value": 61210905982
			},
			{
				"rank": 9,
				"name": "Mathias Bynens",
				"vocation": "Royal Paladin",
				"world": "Vunira",
				"level": 1541,
				"value": 60847825595
			},
			{
				"rank": 10,
				"name": "Lanchadanan",
				"vocation": "Royal Paladin",
				"world": "Vunira",
				"level": 1429,
				"value": 48460562450
			},
			{
				"rank": 11,
				"name": "Bea Charlover Aca",
				"vocation": "Royal Paladin",
				"world": "Vunira",
				"level": 1411,
				"value": 46643347614
			},
			{
				"rank": 12,
				"name": "Reo Light",
				"vocation": "Royal Paladin",
				"world": "Vunira",
				"level": 1410,
				"value": 46568557572
			},
			{
				"rank": 13,
				"name": "Wojjtekk",
				"vocation": "Royal Paladin",
				"world": "Vunira",
				"level": 1401,
				"value": 45651139080
			},
			{
				"rank": 14,
				"name": "Mad Bully",
				"vocation": "Royal Paladin",
				"world": "Vunira",
				"level": 1391,
				"value": 44678032352
			},
			{
				"rank": 15,
				"name": "Yes Yes",
				"vocation": "Royal Paladin",
				"world": "Vunira",
				"level": 1380,
				"value": 43662032369
			},
			{
				"rank": 16,
				"name": "Pastor Koylu",
				"vocation": "Royal Paladin",
				"world": "Vunira",
				"level": 1373,
				"value": 42965539534
			},
			{
				"rank": 17,
				"name": "Kimpsuu",
				"vocation": "Royal Paladin",
				"world": "Vunira",
				"level": 1344,
				"value": 40342695949
			},
			{
				"rank": 18,
				"name": "Zoxerr",
				"vocation": "Royal Paladin",
				"world": "Vunira",
				"level": 1323,
				"value": 38502028660
			},
			{
				"rank": 19,
				"name": "Bluemoon Kimimaro",
				"vocation": "Royal Paladin",
				"world": "Vunira",
				"level": 1306,
				"value": 37021970733
			},
			{
				"rank": 20,
				"name": "Bastu Boris",
				"vocation": "Royal Paladin",
				"world": "Vunira",
				"level": 1304,
				"value": 36828264141
			},
			{
				"rank": 21,
				"name": "Linkirvana",
				"vocation": "Royal Paladin",
				"world": "Vunira",
				"level": 1269,
				"value": 33931770450
			},
			{
				"rank": 22,
				"name": "Galatus",
				"vocation": "Royal Paladin",
				"world": "Vunira",
				"level": 1265,
				"value": 33591666656
			},
			{
				"rank": 23,
				"name": "Anardiel",
				"vocation": "Royal Paladin",
				"world": "Vunira",
				"level": 1249,
				"value": 32333304894
			},
			{
				"rank": 24,
				"name": "Royal druidiaaa",
				"vocation": "Royal Paladin",
				"world": "Vunira",
				"level": 1242,
				"value": 31793147140
			},
			{
				"rank": 25,
				"name": "Gnoors",
				"vocation": "Royal Paladin",
				"world": "Vunira",
				"level": 1220,
				"value": 30118393479
			},
			{
				"rank": 26,
				"name": "Lakroz",
				"vocation": "Royal Paladin",
				"world": "Vunira",
				"level": 1219,
				"value": 30075459455
			},
			{
				"rank": 27,
				"name": "Super Pinchito",
				"vocation": "Royal Paladin",
				"world": "Vunira",
				"level": 1214,
				"value": 29724440098
			},
			{
				"rank": 28,
				"name": "Overlord Dagnars",
				"vocation": "Royal Paladin",
				"world": "Vunira",
				"level": 1183,
				"value": 27456253303
			},
			{
				"rank": 29,
				"name": "Alriken",
				"vocation": "Royal Paladin",
				"world": "Vunira",
				"level": 1180,
				"value": 27248950435
			},
			{
				"rank": 30,
				"name": "Mega Marjan",
				"vocation": "Royal Paladin",
				"world": "Vunira",
				"level": 1175,
				"value": 26956950109
			},
			{
				"rank": 31,
				"name": "Gunner Konrad",
				"vocation": "Royal Paladin",
				"world": "Vunira",
				"level": 1161,
				"value": 26001991479
			},
			{
				"rank": 32,
				"name": "Carpo",
				"vocation": "Royal Paladin",
				"world": "Vunira",
				"level": 1153,
				"value": 25436479084
			},
			{
				"rank": 33,
				"name": "Venus",
				"vocation": "Royal Paladin",
				"world": "Vunira",
				"level": 1149,
				"value": 25181503441
			},
			{
				"rank": 34,
				"name": "Glockad",
				"vocation": "Royal Paladin",
				"world": "Vunira",
				"level": 1126,
				"value": 23688763992
			},
			{
				"rank": 35,
				"name": "Draakz",
				"vocation": "Royal Paladin",
				"world": "Vunira",
				"level": 1123,
				"value": 23482206124
			},
			{
				"rank": 36,
				"name": "Mazzika Raa",
				"vocation": "Royal Paladin",
				"world": "Vunira",
				"level": 1115,
				"value": 23008928525
			},
			{
				"rank": 37,
				"name": "Tad Dzik",
				"vocation": "Royal Paladin",
				"world": "Vunira",
				"level": 1093,
				"value": 21667368682
			},
			{
				"rank": 38,
				"name": "Claq",
				"vocation": "Royal Paladin",
				"world": "Vunira",
				"level": 1085,
				"value": 21200853916
			},
			{
				"rank": 39,
				"name": "King Baani",
				"vocation": "Royal Paladin",
				"world": "Vunira",
				"level": 1077,
				"value": 20750179265
			},
			{
				"rank": 40,
				"name": "Crim Moon",
				"vocation": "Royal Paladin",
				"world": "Vunira",
				"level": 1073,
				"value": 20531428510
			},
			{
				"rank": 41,
				"name": "Krysson",
				"vocation": "Royal Paladin",
				"world": "Vunira",
				"level": 1072,
				"value": 20461492590
			},
			{
				"rank": 42,
				"name": "Pan Szympans",
				"vocation": "Royal Paladin",
				"world": "Vunira",
				"level": 1069,
				"value": 20291006063
			},
			{
				"rank": 43,
				"name": "Kubus Oficjalnie",
				"vocation": "Royal Paladin",
				"world": "Vunira",
				"level": 1052,
				"value": 19332152063
			},
			{
				"rank": 44,
				"name": "Pumpamm",
				"vocation": "Royal Paladin",
				"world": "Vunira",
				"level": 1047,
				"value": 19055882065
			},
			{
				"rank": 45,
				"name": "Maan Temor",
				"vocation": "Royal Paladin",
				"world": "Vunira",
				"level": 1046,
				"value": 19001934132
			},
			{
				"rank": 46,
				"name": "Gala Tuga",
				"vocation": "Royal Paladin",
				"world": "Vunira",
				"level": 1045,
				"value": 18941585821
			},
			{
				"rank": 47,
				"name": "Peexee Charlover",
				"vocation": "Royal Paladin",
				"world": "Vunira",
				"level": 1037,
				"value": 18507150930
			},
			{
				"rank": 48,
				"name": "Vic Del'Sal",
				"vocation": "Royal Paladin",
				"world": "Vunira",
				"level": 1033,
				"value": 18311804865
			},
			{
				"rank": 49,
				"name": "Incun",
				"vocation": "Royal Paladin",
				"world": "Vunira",
				"level": 1033,
				"value": 18266534354
			},
			{
				"rank": 50,
				"name": "Ten Bez Talentny",
				"vocation": "Royal Paladin",
				"world": "Vunira",
				"level": 1031,
				"value": 18186625653
			}
		],
		"highscore_page": {
			"current_page": 1,
			"total_pages": 20,
			"total_records": 1000
		}
	},
	"information": {
		"api": {
			"version": 4,
			"release": "edge",
			"commit": "1a0adebff1bcee8e6e7eba76b5918a5e7ceba663"
		},
		"tibia_urls": [
			"https://www.tibia.com/community/?subtopic=highscores&world=Vunira&category=6&profession=3&currentpage=1"
		],
		"status": {
			"http_code": 200
		}
	}
}
