{
	"highscores": {
		"world": "Vunira",
		"category": "experience",
		"vocation": "paladins",
		"highscore_list": [
			{
				"rank": 1,
				"name": "Partyboost",
				"vocation": "Royal Paladin",
				"world": "Vunira",
				"level": 1955,
				"value": 124160987504
			},
			{
				"rank": 2,
				"name": "Piipexz",
				"vocation": "Royal Paladin",
				"world": "Vunira",
				"level": 1562,
				"value": 63288102150
			},
			{
				"rank": 3,
				"name": "Sinsor",
				"vocation": "Royal Paladin",
				"world": "Vunira",
				"level": 1559,
				"value": 63014088894
			},
			{
				"rank": 4,
				"name": "True Abdosz",
				"vocation": "Royal Paladin",
				"world": "Vunira",
				"level": 1557,
				"value": 62680991400
			},
			{
				"rank": 5,
				"name": "Sabziro",
				"vocation": "Royal Paladin",
				"world": "Vunira",
				"level": 1550,
				"value": 61924471343
			},
			{
				"rank": 6,
				"name": "Saint Tristen",
				"vocation": "Royal Paladin",
				"world": "Vunira",
				"level": 1497,
				"value": 55690698086
			},
			{
				"rank": 7,
				"name": "Nozyk",
				"vocation": "Royal Paladin",
				"world": "Vunira",
				"level": 1480,
				"value": 53829964811
			},
			{
				"rank": 8,
				"name": "Alex Froggy",
				"vocation": "Royal Paladin",
				"world": "Vunira",
				"level": 1409,
				"value": 46488491534
			},
			{
				"rank": 9,
				"name": "Paladino Do luz",
				"vocation": "Royal Paladin",
				"world": "Vunira",
				"level": 1351,
				"value": 40988694130
			},
			{
				"rank": 10,
				"name": "Lanchadanan",
				"vocation": "Royal Paladin",
				"world": "Vunira",
				"level": 1349,
				"value": 40816374959
			},
			{
				"rank": 11,
				"name": "Mathias Bynens",
				"vocation": "Royal Paladin",
				"world": "Vunira",
				"level": 1339,
				"value": 39888542029
			},
			{
				"rank": 12,
				"name": "Reo Light",
				"vocation": "Royal Paladin",
				"world": "Vunira",
				"level": 1339,
				"value": 39880678580
			},
			{
				"rank": 13,
				"name": "Licz mi strzaly",
				"vocation": "Royal Paladin",
				"world": "Vunira",
				"level": 1325,
				"value": 38678193934
			},
			{
				"rank": 14,
				"name": "Roffberto",
				"vocation": "Royal Paladin",
				"world": "Vunira",
				"level": 1325,
				"value": 38605953633
			},
			{
				"rank": 15,
				"name": "Yes Yes",
				"vocation": "Royal Paladin",
				"world": "Vunira",
				"level": 1271,
				"value": 34135257905
			},
			{
				"rank": 16,
				"name": "Zoxerr",
				"vocation": "Royal Paladin",
				"world": "Vunira",
				"level": 1270,
				"value": 34021137912
			},
			{
				"rank": 17,
				"name": "Linkirvana",
				"vocation": "Royal Paladin",
				"world": "Vunira",
				"level": 1269,
				"value": 33931770450
			},
			{
				"rank": 18,
				"name": "Bea Charlover Aca",
				"vocation": "Royal Paladin",
				"world": "Vunira",
				"level": 1259,
				"value": 33136008035
			},
			{
				"rank": 19,
				"name": "Anardiel",
				"vocation": "Royal Paladin",
				"world": "Vunira",
				"level": 1238,
				"value": 31521147034
			},
			{
				"rank": 20,
				"name": "Pastor Koylu",
				"vocation": "Royal Paladin",
				"world": "Vunira",
				"level": 1214,
				"value": 29727881770
			},
			{
				"rank": 21,
				"name": "Kimpsuu",
				"vocation": "Royal Paladin",
				"world": "Vunira",
				"level": 1209,
				"value": 29332063648
			},
			{
				"rank": 22,
				"name": "Namikaze Kimimaro",
				"vocation": "Royal Paladin",
				"world": "Vunira",
				"level": 1208,
				"value": 29243219002
			},
			{
				"rank": 23,
				"name": "Wojjtekk",
				"vocation": "Royal Paladin",
				"world": "Vunira",
				"level": 1207,
				"value": 29228462529
			},
			{
				"rank": 24,
				"name": "Mad Bully",
				"vocation": "Royal Paladin",
				"world": "Vunira",
				"level": 1205,
				"value": 29085530344
			},
			{
				"rank": 25,
				"name": "Lakroz",
				"vocation": "Royal Paladin",
				"world": "Vunira",
				"level": 1202,
				"value": 28854220981
			},
			{
				"rank": 26,
				"name": "Super Pinchito",
				"vocation": "Royal Paladin",
				"world": "Vunira",
				"level": 1178,
				"value": 27169371473
			},
			{
				"rank": 27,
				"name": "Royal druidiaaa",
				"vocation": "Royal Paladin",
				"world": "Vunira",
				"level": 1170,
				"value": 26562815495
			},
			{
				"rank": 28,
				"name": "Darkuuu",
				"vocation": "Royal Paladin",
				"world": "Vunira",
				"level": 1163,
				"value": 26086474046
			},
			{
				"rank": 29,
				"name": "Gnorus",
				"vocation": "Royal Paladin",
				"world": "Vunira",
				"level": 1141,
				"value": 24666286258
			},
			{
				"rank": 30,
				"name": "Venus",
				"vocation": "Royal Paladin",
				"world": "Vunira",
				"level": 1126,
				"value": 23710865913
			},
			{
				"rank": 31,
				"name": "Gubb Sam",
				"vocation": "Royal Paladin",
				"world": "Vunira",
				"level": 1123,
				"value": 23525621676
			},
			{
				"rank": 32,
				"name": "Boris Bomboclaat",
				"vocation": "Royal Paladin",
				"world": "Vunira",
				"level": 1117,
				"value": 23153099268
			},
			{
				"rank": 33,
				"name": "Exevus",
				"vocation": "Royal Paladin",
				"world": "Vunira",
				"level": 1106,
				"value": 22449563695
			},
			{
				"rank": 34,
				"name": "Mega Marjan",
				"vocation": "Royal Paladin",
				"world": "Vunira",
				"level": 1101,
				"value": 22177340682
			},
			{
				"rank": 35,
				"name": "Overlord Assassin",
				"vocation": "Royal Paladin",
				"world": "Vunira",
				"level": 1083,
				"value": 21061457549
			},
			{
				"rank": 36,
				"name": "Claq",
				"vocation": "Royal Paladin",
				"world": "Vunira",
				"level": 1076,
				"value": 20702980365
			},
			{
				"rank": 37,
				"name": "Alriken",
				"vocation": "Royal Paladin",
				"world": "Vunira",
				"level": 1070,
				"value": 20338125648
			},
			{
				"rank": 38,
				"name": "Crim Moon",
				"vocation": "Royal Paladin",
				"world": "Vunira",
				"level": 1067,
				"value": 20145745927
			},
			{
				"rank": 39,
				"name": "Chief Detox",
				"vocation": "Royal Paladin",
				"world": "Vunira",
				"level": 1065,
				"value": 20027851769
			},
			{
				"rank": 40,
				"name": "Mindcrits",
				"vocation": "Royal Paladin",
				"world": "Vunira",
				"level": 1065,
				"value": 20026488922
			},
			{
				"rank": 41,
				"name": "Glockad",
				"vocation": "Royal Paladin",
				"world": "Vunira",
				"level": 1062,
				"value": 19866675885
			},
			{
				"rank": 42,
				"name": "Mazzika Raa",
				"vocation": "Royal Paladin",
				"world": "Vunira",
				"level": 1055,
				"value": 19495092252
			},
			{
				"rank": 43,
				"name": "Draakz",
				"vocation": "Royal Paladin",
				"world": "Vunira",
				"level": 1033,
				"value": 18275446812
			},
			{
				"rank": 44,
				"name": "Vic Del'Sal",
				"vocation": "Royal Paladin",
				"world": "Vunira",
				"level": 1029,
				"value": 18081069489
			},
			{
				"rank": 45,
				"name": "Gala Tuga",
				"vocation": "Royal Paladin",
				"world": "Vunira",
				"level": 1016,
				"value": 17392293053
			},
			{
				"rank": 46,
				"name": "Lukehimself",
				"vocation": "Royal Paladin",
				"world": "Vunira",
				"level": 1013,
				"value": 17224739177
			},
			{
				"rank": 47,
				"name": "Pan Szympans",
				"vocation": "Royal Paladin",
				"world": "Vunira",
				"level": 1010,
				"value": 17081840650
			},
			{
				"rank": 48,
				"name": "King Baani",
				"vocation": "Royal Paladin",
				"world": "Vunira",
				"level": 1009,
				"value": 17066221180
			},
			{
				"rank": 49,
				"name": "Ladyy Aias",
				"vocation": "Royal Paladin",
				"world": "Vunira",
				"level": 1005,
				"value": 16844122858
			},
			{
				"rank": 50,
				"name": "Spawacz Oblivion",
				"vocation": "Royal Paladin",
				"world": "Vunira",
				"level": 1002,
				"value": 16713599670
			}
		],
		"highscore_page": {
			"current_page": 1,
			"total_pages": 20,
			"total_records": 1000
		}
	},
	"information": {
		"api": {
			"version": 4,
			"release": "edge",
			"commit": "acf11e28d68fb2ca314b532dc56a2e18c13d8d68"
		},
		"tibia_urls": [
			"https://www.tibia.com/community/?subtopic=highscores&world=Vunira&category=6&profession=3&currentpage=1"
		],
		"status": {
			"http_code": 200
		}
	}
}
