{
	"highscores": {
		"world": "Vunira",
		"category": "experience",
		"vocation": "paladins",
		"highscore_list": [
			{
				"rank": 1,
				"name": "Partyboost",
				"vocation": "Royal Paladin",
				"world": "Vunira",
				"level": 2017,
				"value": 136437308469
			},
			{
				"rank": 2,
				"name": "True Abdosz",
				"vocation": "Royal Paladin",
				"world": "Vunira",
				"level": 1592,
				"value": 67075839080
			},
			{
				"rank": 3,
				"name": "Sabziro",
				"vocation": "Royal Paladin",
				"world": "Vunira",
				"level": 1583,
				"value": 65973819001
			},
			{
				"rank": 4,
				"name": "Sinsor",
				"vocation": "Royal Paladin",
				"world": "Vunira",
				"level": 1581,
				"value": 65637825172
			},
			{
				"rank": 5,
				"name": "Radrasz",
				"vocation": "Royal Paladin",
				"world": "Vunira",
				"level": 1512,
				"value": 57494331206
			},
			{
				"rank": 6,
				"name": "Nozyk",
				"vocation": "Royal Paladin",
				"world": "Vunira",
				"level": 1508,
				"value": 57001932518
			},
			{
				"rank": 7,
				"name": "Saint Tristen",
				"vocation": "Royal Paladin",
				"world": "Vunira",
				"level": 1507,
				"value": 56814774492
			},
			{
				"rank": 8,
				"name": "Alex Froggy",
				"vocation": "Royal Paladin",
				"world": "Vunira",
				"level": 1459,
				"value": 51625567084
			},
			{
				"rank": 9,
				"name": "Mathias Bynens",
				"vocation": "Royal Paladin",
				"world": "Vunira",
				"level": 1394,
				"value": 45027909127
			},
			{
				"rank": 10,
				"name": "Lanchadanan",
				"vocation": "Royal Paladin",
				"world": "Vunira",
				"level": 1373,
				"value": 43017074781
			},
			{
				"rank": 11,
				"name": "Reo Light",
				"vocation": "Royal Paladin",
				"world": "Vunira",
				"level": 1357,
				"value": 41469221422
			},
			{
				"rank": 12,
				"name": "Yes Yes",
				"vocation": "Royal Paladin",
				"world": "Vunira",
				"level": 1293,
				"value": 35909622082
			},
			{
				"rank": 13,
				"name": "Bea Charlover Aca",
				"vocation": "Royal Paladin",
				"world": "Vunira",
				"level": 1291,
				"value": 35731479532
			},
			{
				"rank": 14,
				"name": "Zoxerr",
				"vocation": "Royal Paladin",
				"world": "Vunira",
				"level": 1284,
				"value": 35163302276
			},
			{
				"rank": 15,
				"name": "Linkirvana",
				"vocation": "Royal Paladin",
				"world": "Vunira",
				"level": 1269,
				"value": 33931770450
			},
			{
				"rank": 16,
				"name": "Pastor Koylu",
				"vocation": "Royal Paladin",
				"world": "Vunira",
				"level": 1249,
				"value": 32366863084
			},
			{
				"rank": 17,
				"name": "Wojjtekk",
				"vocation": "Royal Paladin",
				"world": "Vunira",
				"level": 1242,
				"value": 31839724746
			},
			{
				"rank": 18,
				"name": "Anardiel",
				"vocation": "Royal Paladin",
				"world": "Vunira",
				"level": 1233,
				"value": 31157268594
			},
			{
				"rank": 19,
				"name": "Kimpsuu",
				"vocation": "Royal Paladin",
				"world": "Vunira",
				"level": 1233,
				"value": 31153221340
			},
			{
				"rank": 20,
				"name": "Bluemoon Kimimaro",
				"vocation": "Royal Paladin",
				"world": "Vunira",
				"level": 1229,
				"value": 30839931889
			},
			{
				"rank": 21,
				"name": "Mad Bully",
				"vocation": "Royal Paladin",
				"world": "Vunira",
				"level": 1229,
				"value": 30838837210
			},
			{
				"rank": 22,
				"name": "Lakroz",
				"vocation": "Royal Paladin",
				"world": "Vunira",
				"level": 1205,
				"value": 29036124584
			},
			{
				"rank": 23,
				"name": "Super Pinchito",
				"vocation": "Royal Paladin",
				"world": "Vunira",
				"level": 1201,
				"value": 28739440671
			},
			{
				"rank": 24,
				"name": "Royal druidiaaa",
				"vocation": "Royal Paladin",
				"world": "Vunira",
				"level": 1186,
				"value": 27668040506
			},
			{
				"rank": 25,
				"name": "Bastu Boris",
				"vocation": "Royal Paladin",
				"world": "Vunira",
				"level": 1164,
				"value": 26196452293
			},
			{
				"rank": 26,
				"name": "Gunner Konrad",
				"vocation": "Royal Paladin",
				"world": "Vunira",
				"level": 1149,
				"value": 25201957149
			},
			{
				"rank": 27,
				"name": "Carpo",
				"vocation": "Royal Paladin",
				"world": "Vunira",
				"level": 1138,
				"value": 24493329609
			},
			{
				"rank": 28,
				"name": "Venus",
				"vocation": "Royal Paladin",
				"world": "Vunira",
				"level": 1128,
				"value": 23841150145
			},
			{
				"rank": 29,
				"name": "Gubb Sam",
				"vocation": "Royal Paladin",
				"world": "Vunira",
				"level": 1123,
				"value": 23525621676
			},
			{
				"rank": 30,
				"name": "Mega Marjan",
				"vocation": "Royal Paladin",
				"world": "Vunira",
				"level": 1119,
				"value": 23268860453
			},
			{
				"rank": 31,
				"name": "Exevus",
				"vocation": "Royal Paladin",
				"world": "Vunira",
				"level": 1107,
				"value": 22497527737
			},
			{
				"rank": 32,
				"name": "Overlord Assassin",
				"vocation": "Royal Paladin",
				"world": "Vunira",
				"level": 1103,
				"value": 22302028042
			},
			{
				"rank": 33,
				"name": "Alriken",
				"vocation": "Royal Paladin",
				"world": "Vunira",
				"level": 1097,
				"value": 21938186399
			},
			{
				"rank": 34,
				"name": "Glockad",
				"vocation": "Royal Paladin",
				"world": "Vunira",
				"level": 1080,
				"value": 20911591000
			},
			{
				"rank": 35,
				"name": "Claq",
				"vocation": "Royal Paladin",
				"world": "Vunira",
				"level": 1076,
				"value": 20702980365
			},
			{
				"rank": 36,
				"name": "Mindcrits",
				"vocation": "Royal Paladin",
				"world": "Vunira",
				"level": 1074,
				"value": 20539907128
			},
			{
				"rank": 37,
				"name": "Mazzika Raa",
				"vocation": "Royal Paladin",
				"world": "Vunira",
				"level": 1072,
				"value": 20422451302
			},
			{
				"rank": 38,
				"name": "Crim Moon",
				"vocation": "Royal Paladin",
				"world": "Vunira",
				"level": 1069,
				"value": 20287457518
			},
			{
				"rank": 39,
				"name": "Draakz",
				"vocation": "Royal Paladin",
				"world": "Vunira",
				"level": 1047,
				"value": 19045784141
			},
			{
				"rank": 40,
				"name": "Vic Del'Sal",
				"vocation": "Royal Paladin",
				"world": "Vunira",
				"level": 1032,
				"value": 18214581266
			},
			{
				"rank": 41,
				"name": "Pan Szympans",
				"vocation": "Royal Paladin",
				"world": "Vunira",
				"level": 1021,
				"value": 17636551241
			},
			{
				"rank": 42,
				"name": "Gala Tuga",
				"vocation": "Royal Paladin",
				"world": "Vunira",
				"level": 1020,
				"value": 17599280347
			},
			{
				"rank": 43,
				"name": "King Baani",
				"vocation": "Royal Paladin",
				"world": "Vunira",
				"level": 1018,
				"value": 17491095746
			},
			{
				"rank": 44,
				"name": "Lukehimself",
				"vocation": "Royal Paladin",
				"world": "Vunira",
				"level": 1015,
				"value": 17328513276
			},
			{
				"rank": 45,
				"name": "Ladyy Aias",
				"vocation": "Royal Paladin",
				"world": "Vunira",
				"level": 1007,
				"value": 16945188555
			},
			{
				"rank": 46,
				"name": "Spawacz Oblivion",
				"vocation": "Royal Paladin",
				"world": "Vunira",
				"level": 1002,
				"value": 16713599670
			},
			{
				"rank": 47,
				"name": "Incun",
				"vocation": "Royal Paladin",
				"world": "Vunira",
				"level": 996,
				"value": 16374745962
			},
			{
				"rank": 48,
				"name": "Tad Dzik",
				"vocation": "Royal Paladin",
				"world": "Vunira",
				"level": 986,
				"value": 15879834664
			},
			{
				"rank": 49,
				"name": "Maan Temor",
				"vocation": "Royal Paladin",
				"world": "Vunira",
				"level": 985,
				"value": 15869398268
			},
			{
				"rank": 50,
				"name": "Krysson",
				"vocation": "Royal Paladin",
				"world": "Vunira",
				"level": 983,
				"value": 15772470328
			}
		],
		"highscore_page": {
			"current_page": 1,
			"total_pages": 20,
			"total_records": 1000
		}
	},
	"information": {
		"api": {
			"version": 4,
			"release": "edge",
			"commit": "8e1ad9ccbbaecef06266aa7c6e2d00a7b0b91287"
		},
		"tibia_urls": [
			"https://www.tibia.com/community/?subtopic=highscores&world=Vunira&category=6&profession=3&currentpage=1"
		],
		"status": {
			"http_code": 200
		}
	}
}
